libroadrunner_experimental-2.2.2.data/purelib/roadrunner/__init__.py
libroadrunner_experimental-2.2.2.data/purelib/roadrunner/_roadrunner.so
libroadrunner_experimental-2.2.2.data/purelib/roadrunner/roadrunner.py
libroadrunner_experimental-2.2.2.data/purelib/roadrunner/stochastic/__init__.py
libroadrunner_experimental-2.2.2.data/purelib/roadrunner/stochastic/ensemble.py
libroadrunner_experimental-2.2.2.data/purelib/roadrunner/tests/EcoliCore.xml
libroadrunner_experimental-2.2.2.data/purelib/roadrunner/tests/README.txt
libroadrunner_experimental-2.2.2.data/purelib/roadrunner/tests/RoadRunnerTest.py
libroadrunner_experimental-2.2.2.data/purelib/roadrunner/tests/SBMLTest.py
libroadrunner_experimental-2.2.2.data/purelib/roadrunner/tests/SettingTestsSwigAPI.py
libroadrunner_experimental-2.2.2.data/purelib/roadrunner/tests/TestModelFactory.py
libroadrunner_experimental-2.2.2.data/purelib/roadrunner/tests/_SettingTestsSwigAPI.so
libroadrunner_experimental-2.2.2.data/purelib/roadrunner/tests/_TestModelFactory.so
libroadrunner_experimental-2.2.2.data/purelib/roadrunner/tests/__init__.py
libroadrunner_experimental-2.2.2.data/purelib/roadrunner/tests/__main__.py
libroadrunner_experimental-2.2.2.data/purelib/roadrunner/tests/_picklable_swig.so
libroadrunner_experimental-2.2.2.data/purelib/roadrunner/tests/download_biomodels.py
libroadrunner_experimental-2.2.2.data/purelib/roadrunner/tests/feedback.xml
libroadrunner_experimental-2.2.2.data/purelib/roadrunner/tests/linearPathwayClosed.xml
libroadrunner_experimental-2.2.2.data/purelib/roadrunner/tests/linearPathwayOpen.xml
libroadrunner_experimental-2.2.2.data/purelib/roadrunner/tests/picklable_swig.py
libroadrunner_experimental-2.2.2.data/purelib/roadrunner/tests/test_1.xml
libroadrunner_experimental-2.2.2.data/purelib/roadrunner/tests/test_automaticMoietyConservationAnalysis.py
libroadrunner_experimental-2.2.2.data/purelib/roadrunner/tests/test_forwardSensitivitySolver.py
libroadrunner_experimental-2.2.2.dist-info/AUTHORS.txt
libroadrunner_experimental-2.2.2.dist-info/LICENSE.txt
libroadrunner_experimental-2.2.2.dist-info/METADATA
libroadrunner_experimental-2.2.2.dist-info/NOTICE.txt
libroadrunner_experimental-2.2.2.dist-info/WHEEL
libroadrunner_experimental-2.2.2.dist-info/top_level.txt
libroadrunner_experimental-2.2.2.dist-info/RECORD
