Metadata-Version: 2.1
Name: libroadrunner-experimental
Version: 2.2.2
Summary: libRoadRunner: A simulation and analysis library for SBML
Home-page: http://libroadrunner.org
Author: Andy Somogyi, J Kyle Medley, Lucian Smith, Ciaran Welsh, Herbert Sauro
Author-email: tellurium-discuss@u.washington.edu
License: UNKNOWN
Platform: UNKNOWN
Classifier: Intended Audience :: Science/Research
Classifier: Operating System :: MacOS :: MacOS X
Classifier: Operating System :: Microsoft :: Windows
Classifier: Operating System :: POSIX
Classifier: Programming Language :: C++
License-File: LICENSE.txt
License-File: NOTICE.txt
License-File: AUTHORS.txt
Requires-Dist: numpy (>=1.22.0)
